<annotation>
	<folder>allimages</folder>
	<filename>0026.jpg</filename>
	<path>C:\Users\Rafael Lopes\FaceMaskDetection\V2\RealTimeObjectDetection\Tensorflow\workspace\images\allimages\0026.jpg</path>
	<source>
		<database>Unknown</database>
	</source>
	<size>
		<width>780</width>
		<height>501</height>
		<depth>3</depth>
	</size>
	<segmented>0</segmented>
	<object>
		<name>Com Mascara</name>
		<pose>Unspecified</pose>
		<truncated>0</truncated>
		<difficult>0</difficult>
		<bndbox>
			<xmin>255</xmin>
			<ymin>197</ymin>
			<xmax>334</xmax>
			<ymax>250</ymax>
		</bndbox>
	</object>
	<object>
		<name>Com Mascara</name>
		<pose>Unspecified</pose>
		<truncated>0</truncated>
		<difficult>0</difficult>
		<bndbox>
			<xmin>398</xmin>
			<ymin>196</ymin>
			<xmax>465</xmax>
			<ymax>243</ymax>
		</bndbox>
	</object>
	<object>
		<name>Com Mascara</name>
		<pose>Unspecified</pose>
		<truncated>0</truncated>
		<difficult>0</difficult>
		<bndbox>
			<xmin>436</xmin>
			<ymin>303</ymin>
			<xmax>503</xmax>
			<ymax>348</ymax>
		</bndbox>
	</object>
	<object>
		<name>Com Mascara</name>
		<pose>Unspecified</pose>
		<truncated>0</truncated>
		<difficult>0</difficult>
		<bndbox>
			<xmin>565</xmin>
			<ymin>128</ymin>
			<xmax>633</xmax>
			<ymax>179</ymax>
		</bndbox>
	</object>
	<object>
		<name>Com Mascara</name>
		<pose>Unspecified</pose>
		<truncated>0</truncated>
		<difficult>0</difficult>
		<bndbox>
			<xmin>659</xmin>
			<ymin>135</ymin>
			<xmax>729</xmax>
			<ymax>186</ymax>
		</bndbox>
	</object>
</annotation>