<annotation>
	<folder>allimages</folder>
	<filename>0101.png</filename>
	<path>C:\Users\Rafael Lopes\FaceMaskDetection\V2\RealTimeObjectDetection\Tensorflow\workspace\images\allimages\0101.png</path>
	<source>
		<database>Unknown</database>
	</source>
	<size>
		<width>582</width>
		<height>407</height>
		<depth>3</depth>
	</size>
	<segmented>0</segmented>
	<object>
		<name>Com Mascara</name>
		<pose>Unspecified</pose>
		<truncated>0</truncated>
		<difficult>0</difficult>
		<bndbox>
			<xmin>57</xmin>
			<ymin>214</ymin>
			<xmax>131</xmax>
			<ymax>270</ymax>
		</bndbox>
	</object>
	<object>
		<name>Com Mascara</name>
		<pose>Unspecified</pose>
		<truncated>0</truncated>
		<difficult>0</difficult>
		<bndbox>
			<xmin>161</xmin>
			<ymin>92</ymin>
			<xmax>242</xmax>
			<ymax>155</ymax>
		</bndbox>
	</object>
	<object>
		<name>Com Mascara</name>
		<pose>Unspecified</pose>
		<truncated>0</truncated>
		<difficult>0</difficult>
		<bndbox>
			<xmin>381</xmin>
			<ymin>109</ymin>
			<xmax>458</xmax>
			<ymax>162</ymax>
		</bndbox>
	</object>
</annotation>