<annotation>
	<folder>allimages</folder>
	<filename>0196.jpg</filename>
	<path>C:\Users\Rafael Lopes\FaceMaskDetection\V2\RealTimeObjectDetection\Tensorflow\workspace\images\allimages\0196.jpg</path>
	<source>
		<database>Unknown</database>
	</source>
	<size>
		<width>700</width>
		<height>467</height>
		<depth>3</depth>
	</size>
	<segmented>0</segmented>
	<object>
		<name>Com Mascara</name>
		<pose>Unspecified</pose>
		<truncated>0</truncated>
		<difficult>0</difficult>
		<bndbox>
			<xmin>265</xmin>
			<ymin>150</ymin>
			<xmax>365</xmax>
			<ymax>229</ymax>
		</bndbox>
	</object>
	<object>
		<name>Com Mascara</name>
		<pose>Unspecified</pose>
		<truncated>0</truncated>
		<difficult>0</difficult>
		<bndbox>
			<xmin>367</xmin>
			<ymin>147</ymin>
			<xmax>484</xmax>
			<ymax>229</ymax>
		</bndbox>
	</object>
</annotation>